a_pandas_ex_read_charsep_frames/LICENSE
a_pandas_ex_read_charsep_frames/README.MD
a_pandas_ex_read_charsep_frames/__init__.py
a_pandas_ex_read_charsep_frames/requirements.txt
a_pandas_ex_read_charsep_frames/thirdparty.json
a_pandas_ex_read_charsep_frames-0.10.dist-info/LICENSE.rst
a_pandas_ex_read_charsep_frames-0.10.dist-info/METADATA
a_pandas_ex_read_charsep_frames-0.10.dist-info/WHEEL
a_pandas_ex_read_charsep_frames-0.10.dist-info/top_level.txt
a_pandas_ex_read_charsep_frames-0.10.dist-info/RECORD
