Metadata-Version: 2.1
Name: a-pandas-ex-read-charsep-frames
Version: 0.10
Summary: Reads data separated by any char  
Home-page: https://github.com/hansalemaos/a_pandas_ex_read_charsep_frames
Author: Johannes Fischer
Author-email: <aulasparticularesdealemaosp@gmail.com>
License: MIT
Keywords: pandas,csv,read
Classifier: Development Status :: 4 - Beta
Classifier: Programming Language :: Python :: 3 :: Only
Classifier: Programming Language :: Python :: 3.9
Classifier: Topic :: Scientific/Engineering :: Visualization
Classifier: Topic :: Software Development :: Libraries :: Python Modules
Classifier: Topic :: Text Editors :: Text Processing
Classifier: Topic :: Text Processing :: General
Classifier: Topic :: Text Processing :: Indexing
Classifier: Topic :: Text Processing :: Filters
Classifier: Topic :: Utilities
License-File: LICENSE.rst
Requires-Dist: a-pandas-ex-horizontal-explode
Requires-Dist: normalize-lists
Requires-Dist: pandas
